ipython_playground/__init__.py
ipython_playground/create.py
ipython_playground/database.py
ipython_playground/extras.py
ipython_playground/redis.py
ipython_playground/utils.py
ipython_playground-0.4.1.dist-info/METADATA
ipython_playground-0.4.1.dist-info/WHEEL
ipython_playground-0.4.1.dist-info/entry_points.txt
ipython_playground-0.4.1.dist-info/licenses/LICENSE.md
ipython_playground-0.4.1.dist-info/RECORD
