Metadata-Version: 2.4
Name: ipython-playground
Version: 0.4.1
Summary: Understand what is in your ipython playground.
Project-URL: Repository, https://github.com/iloveitaly/ipython-playground
Author-email: Michael Bianco <mike@mikebian.co>
License: MIT
License-File: LICENSE.md
Keywords: ipython,playground,repl
Requires-Python: >=3.9
Requires-Dist: rich>=13.9.4
